README.md
setup.cfg
setup.py
distobjects/__init__.py
distobjects/core.py
distobjects/exceptions.py
distobjects/fields.py
distobjects.egg-info/PKG-INFO
distobjects.egg-info/SOURCES.txt
distobjects.egg-info/dependency_links.txt
distobjects.egg-info/requires.txt
distobjects.egg-info/top_level.txt
distobjects/backends/__init__.py
distobjects/backends/redis.py