Metadata-Version: 2.1
Name: distobjects
Version: 0.0.1a1
Summary: Python library to easily map Objects to Caching Systems like Redis
Home-page: https://github.com/svrdev27/py-distobjects
License: GPLv3
Download-URL: https://github.com/svrdev27/py-distobjects/archive/v0.0.1-alpha.1.tar.gz
Keywords: redis,ODM,distributed objects,caching
Platform: UNKNOWN
Classifier: Development Status :: 3 - Alpha
Classifier: Intended Audience :: Developers
Classifier: Topic :: Software Development
Classifier: License :: OSI Approved :: GNU General Public License v3 (GPLv3)
Classifier: Programming Language :: Python :: 3
Classifier: Programming Language :: Python :: 3.4
Classifier: Programming Language :: Python :: 3.5
Classifier: Programming Language :: Python :: 3.6
Classifier: Programming Language :: Python :: 3.7
